administ/__init__.py
administ/middleware.py
django_administ-1.0.1.dist-info/DESCRIPTION.rst
django_administ-1.0.1.dist-info/METADATA
django_administ-1.0.1.dist-info/RECORD
django_administ-1.0.1.dist-info/WHEEL
django_administ-1.0.1.dist-info/metadata.json
django_administ-1.0.1.dist-info/top_level.txt
